altbacken/__init__.py
altbacken/core/__init__.py
altbacken/core/analysis.py
altbacken/core/annealing.py
altbacken/core/neighbourhood.py
altbacken/core/state.py
altbacken/external/__init__.py
altbacken/external/acceptance.py
altbacken/external/annealing.py
altbacken/external/neighbourhood/__init__.py
altbacken/external/neighbourhood/numeric.py
altbacken/external/neighbourhood/permutation.py
altbacken/external/report/__init__.py
altbacken/external/report/plot.py
altbacken/external/stop.py
altbacken/external/temperature.py
altbacken/internal/__init__.py
altbacken/internal/analysis/__init__.py
altbacken/internal/analysis/acceptance.py
altbacken/internal/analysis/base.py
altbacken/internal/analysis/convergence.py
altbacken/internal/neighbourhood.py
altbacken/internal/report/__init__.py
altbacken/internal/report/base.py
altbacken/internal/report/file.py
altbacken/internal/report/logging.py
altbacken/internal/report/memory.py
altbacken/internal/stop/__init__.py
altbacken/internal/stop/compound.py
altbacken/internal/tracer/__init__.py
altbacken/optional/__init__.py
altbacken/optional/loguru.py
altbacken/optional/numpy.py
altbacken-0.8.0.dist-info/METADATA
altbacken-0.8.0.dist-info/WHEEL
altbacken-0.8.0.dist-info/licenses/LICENSE
altbacken-0.8.0.dist-info/RECORD
