Metadata-Version: 2.4
Name: altbacken
Version: 0.8.0
Summary: Package for running simulated annealing.
License: MIT
License-File: LICENSE
Keywords: simulated annealing,metaheuristics,optimization,heuristic search
Author: voidpointercast
Author-email: voidpointercast@justmail.de
Requires-Python: >=3.14,<4.0
Classifier: Development Status :: 3 - Alpha
Classifier: Intended Audience :: Science/Research
Classifier: Intended Audience :: Developers
Classifier: License :: OSI Approved :: MIT License
Classifier: Programming Language :: Python :: 3
Classifier: Programming Language :: Python :: 3 :: Only
Classifier: Operating System :: OS Independent
Classifier: Topic :: Scientific/Engineering :: Artificial Intelligence
Classifier: Topic :: Scientific/Engineering :: Mathematics
Classifier: Topic :: Software Development :: Libraries :: Python Modules
Classifier: Natural Language :: English
Requires-Dist: more-itertools (>=10.8.0,<11.0.0)
Project-URL: Documentation, https://altbacken.readthedocs.io/en/latest/
Project-URL: Homepage, https://gitlab.com/patrick.daniel.gress/altbacken
Project-URL: Repository, https://gitlab.com/patrick.daniel.gress/altbacken
